openstep_parser/__init__.py
openstep_parser/openstep_parser.py
openstep_parser-1.5.4.dist-info/LICENSE
openstep_parser-1.5.4.dist-info/METADATA
openstep_parser-1.5.4.dist-info/WHEEL
openstep_parser-1.5.4.dist-info/top_level.txt
openstep_parser-1.5.4.dist-info/RECORD
